[
    {
        "id": "99116810474405516",
        "title": "S\u00e9curit\u00e9, territoire, population cours au Coll\u00e8ge de France (1977-1978)",
        "creator": "Foucault, Michel 1926-1984",
        "date": "2004",
        "publisher": "Seuil; Gallimard",
        "isbn": "2020307995",
        "thumbnail": "",
        "dewey": "Political science (Politics and government)",
        "added": "2022-04-22",
        "support": "physical"
    },
    {
        "id": "99116810474705516",
        "title": "L'empire de l'universit\u00e9 sur Bourdieu, les intellectuels et le journalisme",
        "creator": "Lagasnerie, Geoffroy <<de>> 1982-",
        "date": "2007",
        "publisher": "Editions Amsterdam",
        "isbn": "9782915547535",
        "thumbnail": "",
        "dewey": "History & geography",
        "added": "2022-04-11",
        "support": "physical"
    },
    {
        "id": "99116810474305516",
        "title": "Un f\u00e9minisme d\u00e9colonial",
        "creator": "Verg\u00e8s, Fran\u00e7oise 1952- Verfasser",
        "date": "[2019]",
        "publisher": "La Fabrique \u00e9ditions",
        "isbn": "9782358721745",
        "thumbnail": "",
        "dewey": "Political science (Politics and government)",
        "added": "2022-04-05",
        "support": "physical"
    },
    {
        "id": "99116810475105516",
        "title": "Redesigning the American dream the future of housing, work, and family life",
        "creator": "Hayden, Dolores 1945- Verfasser",
        "date": "[2002]",
        "publisher": "WW Norton & Company",
        "isbn": "9780393730944",
        "thumbnail": "",
        "dewey": "Area planning and landscape architecture",
        "added": "2022-03-28",
        "support": "physical"
    },
    {
        "id": "99116809168905516",
        "title": "How to be an anticapitalist in the twenty-first century",
        "creator": "Wright, Erik Olin 1947-2019 Verfasser",
        "date": "[2021]",
        "publisher": "Verso",
        "isbn": "9781788739559",
        "thumbnail": "",
        "dewey": "Social sciences",
        "added": "2022-03-21",
        "support": "physical"
    },
    {
        "id": "99116809169205516",
        "title": "The xenofeminist manifesto a politics for alienation",
        "creator": "Cuboniks, Laboria Verfasser",
        "date": "2018",
        "publisher": "Verso",
        "isbn": "9781788731577",
        "thumbnail": "",
        "dewey": "",
        "added": "2022-03-21",
        "support": "physical"
    },
    {
        "id": "99116809169305516",
        "title": "Burn it down! feminist manifestos for the revolution",
        "creator": "",
        "date": "2020",
        "publisher": "Verso",
        "isbn": "9781788735384",
        "thumbnail": "",
        "dewey": "Social sciences",
        "added": "2022-03-21",
        "support": "physical"
    },
    {
        "id": "99116809169505516",
        "title": "Making space women and the man-made environment",
        "creator": "",
        "date": "2022",
        "publisher": "Verso",
        "isbn": "1839765712",
        "thumbnail": "",
        "dewey": "Area planning and landscape architecture",
        "added": "2022-03-21",
        "support": "physical"
    },
    {
        "id": "99116810474805516",
        "title": "All about love new visions",
        "creator": "hooks, bell 1952-2021",
        "date": "2018",
        "publisher": "William Morrow",
        "isbn": "0060959479",
        "thumbnail": "",
        "dewey": "Philosophy & psychology",
        "added": "2022-03-21",
        "support": "physical"
    },
    {
        "id": "99116810874605516",
        "title": "The Revolutionary Urbanism of Street Farm Eco-Anarchism, Architecture and Alternative Technology in the 1970s",
        "creator": "Hunt, Stephen E.",
        "date": "2014",
        "publisher": "Tangent Books",
        "isbn": "1906477442",
        "thumbnail": "",
        "dewey": "Architecture",
        "added": "2022-03-16",
        "support": "physical"
    },
    {
        "id": "99116809169405516",
        "title": "If they come in the morning voices of resistance",
        "creator": "",
        "date": "2016",
        "publisher": "Verso",
        "isbn": "1784787698",
        "thumbnail": "",
        "dewey": "Penal and related institutions",
        "added": "2022-03-15",
        "support": "physical"
    },
    {
        "id": "99116810472005516",
        "title": "Living a feminist life /",
        "creator": "Ahmed, Sara, 1969- author.",
        "date": "2017.",
        "publisher": "Duke University Press",
        "isbn": "9780822363040",
        "thumbnail": "",
        "dewey": "Groups of people",
        "added": "2022-03-09",
        "support": "electronic"
    },
    {
        "id": "99116811075005516",
        "title": "Making Space : Women and the Manmade Environment.",
        "creator": "Matrix.",
        "date": "2022.",
        "publisher": "Verso Books",
        "isbn": "1839765739",
        "thumbnail": "",
        "dewey": "Architecture",
        "added": "2022-03-09",
        "support": "electronic"
    },
    {
        "id": "99116808867605516",
        "title": "Altering practices feminist politics and poetics of space /",
        "creator": "",
        "date": "2007",
        "publisher": "Routledge",
        "isbn": "1134325339",
        "thumbnail": "",
        "dewey": "Architecture",
        "added": "2022-03-08",
        "support": "electronic"
    },
    {
        "id": "99116808867705516",
        "title": "Women and space : ground rules and social maps /",
        "creator": "",
        "date": "[2020]",
        "publisher": "Routledge",
        "isbn": "1003135080",
        "thumbnail": "",
        "dewey": "Groups of people",
        "added": "2022-03-08",
        "support": "electronic"
    },
    {
        "id": "99116808867805516",
        "title": "The battle for Tolmers Square /",
        "creator": "Wates, Nick., author.",
        "date": "2013.",
        "publisher": "Routledge",
        "isbn": "1135120706",
        "thumbnail": "",
        "dewey": "Economics of land and energy",
        "added": "2022-03-08",
        "support": "electronic"
    },
    {
        "id": "99116808867905516",
        "title": "Space, gender, knowledge : feminist readings /",
        "creator": "",
        "date": "2016.",
        "publisher": "Routledge",
        "isbn": "1315824876",
        "thumbnail": "",
        "dewey": "Geography and travel",
        "added": "2022-03-08",
        "support": "electronic"
    },
    {
        "id": "99116808868005516",
        "title": "Remaking cities : contradictions of the recent urban environment /",
        "creator": "Ravetz, Alison.",
        "date": "2013.",
        "publisher": "Routledge",
        "isbn": "1135007020",
        "thumbnail": "",
        "dewey": "Communities",
        "added": "2022-03-08",
        "support": "electronic"
    },
    {
        "id": "99116808868105516",
        "title": "New Space For Women /",
        "creator": "Wekerle, Gerda R, author.",
        "date": "[2019].",
        "publisher": "Taylor and Francis an imprint of Routledge",
        "isbn": "0367169002",
        "thumbnail": "",
        "dewey": "Groups of people",
        "added": "2022-03-08",
        "support": "electronic"
    },
    {
        "id": "99116808868205516",
        "title": "Mapping Desire Geographies of Sexuality.",
        "creator": "Bell, David.",
        "date": "1995.",
        "publisher": "Routledge",
        "isbn": "1280021683",
        "thumbnail": "",
        "dewey": "Culture and institutions",
        "added": "2022-03-08",
        "support": "electronic"
    },
    {
        "id": "99116808868305516",
        "title": "Homes Fit For Heroes : The Politics and Architecture of Early State Housing in Britain /",
        "creator": "Swenarton, Mark , author.",
        "date": "[2018].",
        "publisher": "Routledge",
        "isbn": "0429762682",
        "thumbnail": "",
        "dewey": "Other social problems and services",
        "added": "2022-03-08",
        "support": "electronic"
    },
    {
        "id": "99116808868405516",
        "title": "Exploring human geography : a reader /",
        "creator": "",
        "date": "2014.",
        "publisher": "Routledge",
        "isbn": "047023542X",
        "thumbnail": "",
        "dewey": "Factors affecting social behavior",
        "added": "2022-03-08",
        "support": "electronic"
    },
    {
        "id": "99116808868505516",
        "title": "Buildings and society : essays on the social development of the built environment /",
        "creator": "",
        "date": "1984, c1980.",
        "publisher": "Routledge & Kegan Paul",
        "isbn": "1135795282",
        "thumbnail": "",
        "dewey": "Architectural materials and structure",
        "added": "2022-03-08",
        "support": "electronic"
    },
    {
        "id": "990116010790205516",
        "title": "Manuel de sociologie des mobilit\u00e9s g\u00e9ographiques",
        "creator": "Belton-Chevallier, Leslie 1981-....",
        "date": "[2019]",
        "publisher": "Presses universitaires Fran\u00e7ois-Rabelais",
        "isbn": "2869067135",
        "thumbnail": "",
        "dewey": "Communities",
        "added": "2022-02-18",
        "support": "physical"
    },
    {
        "id": "99116778206605516",
        "title": "La ville en planches bande dessin\u00e9e et mondes urbains",
        "creator": "",
        "date": "[2021]",
        "publisher": "Hermann",
        "isbn": "9791037008367",
        "thumbnail": "",
        "dewey": "Drawing and drawings",
        "added": "2022-02-02",
        "support": "physical"
    },
    {
        "id": "99116787813805516",
        "title": "The arsenal of exclusion & inclusion",
        "creator": "Armborst, Tobias 19..-....",
        "date": "[2021]",
        "publisher": "ACTAR",
        "isbn": "1948765748",
        "thumbnail": "",
        "dewey": "Area planning (Civic art)",
        "added": "2022-01-31",
        "support": "physical"
    },
    {
        "id": "99116786511505516",
        "title": "Operative mapping maps as design tools",
        "creator": "Paez i Blanch, Roger Verfasser",
        "date": "2019",
        "publisher": "ELISAVA Barcelona School of Design and Engineering; Actar Publishers",
        "isbn": "9781948765077",
        "thumbnail": "",
        "dewey": "Architecture from 1400",
        "added": "2022-01-26",
        "support": "physical"
    },
    {
        "id": "99116798265005516",
        "title": "The rational factory architecture, technology, and work in America's age of mass production",
        "creator": "Biggs, Lindy",
        "date": "[1996]",
        "publisher": "Johns Hopkins University Press",
        "isbn": "9780801852619",
        "thumbnail": "",
        "dewey": "",
        "added": "2022-01-26",
        "support": "physical"
    },
    {
        "id": "99116778211805516",
        "title": "Urban playground how child-friendly planning and design can save cities",
        "creator": "Gill, Tim 1953-",
        "date": "[2021]",
        "publisher": "RIBA Publishing",
        "isbn": "9781859469293",
        "thumbnail": "",
        "dewey": "Area planning and landscape architecture",
        "added": "2022-01-24",
        "support": "physical"
    },
    {
        "id": "99116778212205516",
        "title": "Riyadh transforming a desert city",
        "creator": "Elsheshtawy, Yasser",
        "date": "2022",
        "publisher": "Routledge",
        "isbn": "9780367485177",
        "thumbnail": "",
        "dewey": "Social sciences",
        "added": "2022-01-24",
        "support": "physical"
    },
    {
        "id": "99116778212405516",
        "title": "Platform urbanism and its discontents",
        "creator": "Mostra internazionale di architettura Venedig 2021 17.",
        "date": "[2021]",
        "publisher": "nai010 Publishers",
        "isbn": "946208615X",
        "thumbnail": "",
        "dewey": "Architecture",
        "added": "2022-01-24",
        "support": "physical"
    },
    {
        "id": "99116778212705516",
        "title": "Planning and participation",
        "creator": "O'Hare, Paul 19..-....",
        "date": "2021",
        "publisher": "Lund Humphries Publishers Ltd",
        "isbn": "1848224273",
        "thumbnail": "",
        "dewey": "Area planning and landscape architecture",
        "added": "2022-01-24",
        "support": "physical"
    },
    {
        "id": "99116778212805516",
        "title": "Participate! portraits of cities and citizens in action",
        "creator": "",
        "date": "[2021]",
        "publisher": "nai010 publishers",
        "isbn": "9789462086319",
        "thumbnail": "",
        "dewey": "Social sciences",
        "added": "2022-01-24",
        "support": "physical"
    },
    {
        "id": "99116778213405516",
        "title": "Children and planning",
        "creator": "Freeman, Claire auteur",
        "date": "2019",
        "publisher": "Lund Humphries",
        "isbn": "9781848223141",
        "thumbnail": "",
        "dewey": "Area planning and landscape architecture",
        "added": "2022-01-24",
        "support": "physical"
    },
    {
        "id": "990108596580205516",
        "title": "Les paradoxes de la mobilit\u00e9 bouger, s'enraciner",
        "creator": "Kaufmann, Vincent 1969- Verfasser",
        "date": "2017",
        "publisher": "Presses polytechniques et universitaires romandes",
        "isbn": "9782889151981",
        "thumbnail": "",
        "dewey": "Social sciences",
        "added": "2022-01-20",
        "support": "physical"
    },
    {
        "id": "99116778207905516",
        "title": "Construire plus vite la ville durable nouveau mod\u00e8le et partenariats",
        "creator": "",
        "date": "2021",
        "publisher": "Eyrolles",
        "isbn": "9782416002571",
        "thumbnail": "",
        "dewey": "Area planning and landscape architecture",
        "added": "2022-01-12",
        "support": "physical"
    },
    {
        "id": "99116783213805516",
        "title": "Berlin maps",
        "creator": "",
        "date": "[2021]",
        "publisher": "Ruby Press",
        "isbn": "394407436X",
        "thumbnail": "",
        "dewey": "Maps and plans of surface of earth",
        "added": "2022-01-12",
        "support": "physical"
    }
]