[
    {
        "id": "99116898835905516",
        "title": "Next-generation thermal insulation challenges and opportunities /",
        "creator": "",
        "date": "2014",
        "publisher": "ASTM International",
        "isbn": "0803175949",
        "thumbnail": "",
        "dewey": "Specific materials & purposes",
        "added": "2023-03-27",
        "support": "electronic"
    },
    {
        "id": "99116898836005516",
        "title": "Continuous soil gas measurements : worst case risk parameters /",
        "creator": "",
        "date": "[2013]",
        "publisher": "ASTM International",
        "isbn": "0803175868",
        "thumbnail": "",
        "dewey": "Sanitary engineering",
        "added": "2023-03-27",
        "support": "electronic"
    },
    {
        "id": "99116898836105516",
        "title": "Mechanical properties of frozen soils /",
        "creator": "",
        "date": "[2013]",
        "publisher": "ASTM International",
        "isbn": "0803175779",
        "thumbnail": "",
        "dewey": "Civil engineering",
        "added": "2023-03-27",
        "support": "electronic"
    },
    {
        "id": "99116898840605516",
        "title": "Fatigue and fracture mechanics.",
        "creator": "",
        "date": "2012.",
        "publisher": "ASTM International",
        "isbn": "0803175582",
        "thumbnail": "",
        "dewey": "",
        "added": "2023-03-27",
        "support": "electronic"
    },
    {
        "id": "99116898840705516",
        "title": "Durability of building and construction sealants and adhesives : 4th volume",
        "creator": "ASTM Symposium on Durability of Building and Construction Sealants and Adhesives Anaheim, Calif.) 2011 : (4th :; ASTM Symposium on Durability of Building and Construction Sealants and Adhesives Corporate Author",
        "date": "2012",
        "publisher": "ASTM International",
        "isbn": "0803175574",
        "thumbnail": "",
        "dewey": "",
        "added": "2023-03-27",
        "support": "electronic"
    },
    {
        "id": "99116898840805516",
        "title": "Static and dynamic spinal implants : are we evaluating them appropriately",
        "creator": "",
        "date": "2012",
        "publisher": "ASTM International",
        "isbn": "0803194188",
        "thumbnail": "",
        "dewey": "Surgery & related medical specialties",
        "added": "2023-03-27",
        "support": "electronic"
    },
    {
        "id": "99116898840905516",
        "title": "Film and nucleate boiling processes",
        "creator": "",
        "date": "2012",
        "publisher": "ASTM International",
        "isbn": "0803188951",
        "thumbnail": "",
        "dewey": "Heat",
        "added": "2023-03-27",
        "support": "electronic"
    },
    {
        "id": "99116898841005516",
        "title": "18th international federation for heat treatment and surface engineering",
        "creator": "International Federation for Heat Treatment and Surface Engineering Congress Corporate Author",
        "date": "2012",
        "publisher": "ASTM International",
        "isbn": "080319417X",
        "thumbnail": "",
        "dewey": "Metalworking & primary metal products",
        "added": "2023-03-27",
        "support": "electronic"
    },
    {
        "id": "99116898841105516",
        "title": "Proceedings of the International Association of Hydrological Sciences",
        "creator": "",
        "date": "",
        "publisher": "Copernicus GmbH",
        "isbn": "",
        "thumbnail": "",
        "dewey": "",
        "added": "2023-03-27",
        "support": "electronic"
    },
    {
        "id": "99116898841205516",
        "title": "Fire resistant fluids",
        "creator": "",
        "date": "2014",
        "publisher": "ASTM International",
        "isbn": "1680159801",
        "thumbnail": "",
        "dewey": "Sanitary engineering",
        "added": "2023-03-27",
        "support": "electronic"
    },
    {
        "id": "99116898841305516",
        "title": "Multicylinder Test Sequences for Evaluating Automotive Engine Oils: Pt. 1: Sequence IID",
        "creator": "Committee D02 Staff Corporate Author",
        "date": "1980",
        "publisher": "American Society for Testing & Materials",
        "isbn": "0803147643",
        "thumbnail": "",
        "dewey": "",
        "added": "2023-03-27",
        "support": "electronic"
    },
    {
        "id": "99116898845805516",
        "title": "PCIM Asia 2022; International Exhibition and Conference for Power Electronics, Intelligent Motion, Renewable Energy and Energy Management",
        "creator": "",
        "date": "2022",
        "publisher": "VDE",
        "isbn": "380075911X",
        "thumbnail": "",
        "dewey": "",
        "added": "2023-03-27",
        "support": "electronic"
    },
    {
        "id": "99116898845905516",
        "title": "ISCTT 2022; 7th International Conference on Information Science, Computer Technology and Transportation",
        "creator": "",
        "date": "2022",
        "publisher": "VDE",
        "isbn": "3800760061",
        "thumbnail": "",
        "dewey": "",
        "added": "2023-03-27",
        "support": "electronic"
    },
    {
        "id": "99116898846005516",
        "title": "European Wireless 2022; 27th European Wireless Conference",
        "creator": "",
        "date": "2022",
        "publisher": "VDE",
        "isbn": "3800760010",
        "thumbnail": "",
        "dewey": "",
        "added": "2023-03-27",
        "support": "electronic"
    },
    {
        "id": "99116898846105516",
        "title": "Communication Cable Networks; 29th ITG Symposium",
        "creator": "",
        "date": "2022",
        "publisher": "VDE",
        "isbn": "3800759977",
        "thumbnail": "",
        "dewey": "",
        "added": "2023-03-27",
        "support": "electronic"
    },
    {
        "id": "99116898846205516",
        "title": "BIBE 2022; The 6th International Conference on Biological Information and Biomedical Engineering",
        "creator": "",
        "date": "2022",
        "publisher": "VDE",
        "isbn": "3800759640",
        "thumbnail": "",
        "dewey": "",
        "added": "2023-03-27",
        "support": "electronic"
    },
    {
        "id": "99116898850405516",
        "title": "Masonry 2022: Advancing Masonry Technology",
        "creator": "",
        "date": "2022",
        "publisher": "ASTM International",
        "isbn": "",
        "thumbnail": "",
        "dewey": "",
        "added": "2023-03-27",
        "support": "electronic"
    },
    {
        "id": "99116898850505516",
        "title": "Progress in Additive Manufacturing 2021",
        "creator": "",
        "date": "2022",
        "publisher": "ASTM International",
        "isbn": "",
        "thumbnail": "",
        "dewey": "",
        "added": "2023-03-27",
        "support": "electronic"
    },
    {
        "id": "99116898850605516",
        "title": "More Than a Glitch : Confronting Race, Gender, and Ability Bias in Tech.",
        "creator": "Broussard, Meredith.",
        "date": "2023.",
        "publisher": "MIT Press",
        "isbn": "026237305X",
        "thumbnail": "",
        "dewey": "Social processes",
        "added": "2023-03-27",
        "support": "electronic"
    },
    {
        "id": "99116898852005516",
        "title": "Rolling Bearing Steel: Design, Technology, Testing and Measurements",
        "creator": "",
        "date": "2022",
        "publisher": "ASTM International",
        "isbn": "",
        "thumbnail": "",
        "dewey": "",
        "added": "2023-03-27",
        "support": "electronic"
    },
    {
        "id": "99116898853605516",
        "title": "Society for Industrial and Applied Mathematics. Proceedings of the SIAM International Conference on Data Mining",
        "creator": "",
        "date": "2001",
        "publisher": "Society for Industrial and Applied Mathematics",
        "isbn": "",
        "thumbnail": "",
        "dewey": "",
        "added": "2023-03-27",
        "support": "electronic"
    },
    {
        "id": "99116898853705516",
        "title": "International Conference on Management and Industrial Engineering",
        "creator": "",
        "date": "2005",
        "publisher": "Niculescu Publishing House",
        "isbn": "",
        "thumbnail": "",
        "dewey": "",
        "added": "2023-03-27",
        "support": "electronic"
    },
    {
        "id": "99116898853805516",
        "title": "Just food : where locavores get it wrong and how we can truly eat responsibly /",
        "creator": "McWilliams, James E., author.",
        "date": "[2009]",
        "publisher": "Little Brown and Company",
        "isbn": "0316052639",
        "thumbnail": "http://books.google.com/books/content?id=nQ86AQAAQBAJ&printsec=frontcover&img=1&zoom=1&edge=curl&source=gbs_api",
        "dewey": "General customs",
        "added": "2023-03-27",
        "support": "electronic"
    },
    {
        "id": "99116898855505516",
        "title": "2022 IEEE/ACIS 23rd International Conference on Software Engineering, Artificial Intelligence, Networking and Parallel/Distributed Computing (SNPD)",
        "creator": "",
        "date": "",
        "publisher": "IEEE Computer Society",
        "isbn": "9798350310412",
        "thumbnail": "",
        "dewey": "",
        "added": "2023-03-27",
        "support": "electronic"
    },
    {
        "id": "99116898855605516",
        "title": "2023 International Conference on Power Electronics and Energy (ICPEE)",
        "creator": "",
        "date": "2023",
        "publisher": "IEEE",
        "isbn": "1665470585",
        "thumbnail": "",
        "dewey": "",
        "added": "2023-03-27",
        "support": "electronic"
    },
    {
        "id": "99116898855705516",
        "title": "2023 International Conference on Electronics, Information, and Communication (ICEIC)",
        "creator": "",
        "date": "2023",
        "publisher": "IEEE",
        "isbn": "9798350320213",
        "thumbnail": "",
        "dewey": "",
        "added": "2023-03-27",
        "support": "electronic"
    },
    {
        "id": "99116898855805516",
        "title": "2023 31st Southern African Universities Power Engineering Conference (SAUPEC)",
        "creator": "",
        "date": "2023",
        "publisher": "IEEE",
        "isbn": "9798350331868",
        "thumbnail": "",
        "dewey": "",
        "added": "2023-03-27",
        "support": "electronic"
    },
    {
        "id": "99116898855905516",
        "title": "2022 Third International Conference on Digital Creation in Arts, Media and Technology (ARTeFACTo)",
        "creator": "",
        "date": "2022",
        "publisher": "IEEE",
        "isbn": "9798350310030",
        "thumbnail": "",
        "dewey": "",
        "added": "2023-03-27",
        "support": "electronic"
    },
    {
        "id": "99116898856005516",
        "title": "2022 OITS International Conference on Information Technology (OCIT)",
        "creator": "",
        "date": "2022",
        "publisher": "IEEE",
        "isbn": "1665493488",
        "thumbnail": "",
        "dewey": "",
        "added": "2023-03-27",
        "support": "electronic"
    },
    {
        "id": "99116898856105516",
        "title": "2022 International Conference on Technologies and Applications of Artificial Intelligence (TAAI)",
        "creator": "",
        "date": "2022",
        "publisher": "IEEE",
        "isbn": "9798350399516",
        "thumbnail": "",
        "dewey": "",
        "added": "2023-03-27",
        "support": "electronic"
    },
    {
        "id": "99116898856205516",
        "title": "2022 IEEE Future Networks World Forum (FNWF)",
        "creator": "",
        "date": "2022",
        "publisher": "IEEE",
        "isbn": "1665462515",
        "thumbnail": "",
        "dewey": "",
        "added": "2023-03-27",
        "support": "electronic"
    },
    {
        "id": "99116898856305516",
        "title": "2022 IEEE 7th Southern Power Electronics Conference (SPEC)",
        "creator": "",
        "date": "2022",
        "publisher": "IEEE",
        "isbn": "9798350399882",
        "thumbnail": "",
        "dewey": "",
        "added": "2023-03-27",
        "support": "electronic"
    },
    {
        "id": "99116898856405516",
        "title": "2022 IEEE 29th International Conference on High Performance Computing, Data and Analytics Workshop (HiPCW)",
        "creator": "",
        "date": "2022",
        "publisher": "IEEE",
        "isbn": "9798350333886",
        "thumbnail": "",
        "dewey": "",
        "added": "2023-03-27",
        "support": "electronic"
    },
    {
        "id": "99116898856505516",
        "title": "2022 Fourth International Conference on Cognitive Computing and Information Processing (CCIP)",
        "creator": "",
        "date": "2022",
        "publisher": "IEEE",
        "isbn": "1665456485",
        "thumbnail": "",
        "dewey": "",
        "added": "2023-03-27",
        "support": "electronic"
    },
    {
        "id": "99116898856605516",
        "title": "2022 7th International Conference on Robotics and Automation Engineering (ICRAE)",
        "creator": "",
        "date": "2022",
        "publisher": "IEEE",
        "isbn": "1665489197",
        "thumbnail": "",
        "dewey": "",
        "added": "2023-03-27",
        "support": "electronic"
    },
    {
        "id": "99116898856705516",
        "title": "2022 6th International Conference on Information Technology, Information Systems and Electrical Engineering (ICITISEE)",
        "creator": "",
        "date": "2022",
        "publisher": "IEEE",
        "isbn": "9798350399622",
        "thumbnail": "",
        "dewey": "",
        "added": "2023-03-27",
        "support": "electronic"
    },
    {
        "id": "99116898856805516",
        "title": "2022 5th International Seminar on Research of Information Technology and Intelligent Systems (ISRITI)",
        "creator": "",
        "date": "2022",
        "publisher": "IEEE",
        "isbn": "1665455128",
        "thumbnail": "",
        "dewey": "",
        "added": "2023-03-27",
        "support": "electronic"
    },
    {
        "id": "99116898856905516",
        "title": "2022 56th Asilomar Conference on Signals, Systems, and Computers",
        "creator": "",
        "date": "2022",
        "publisher": "IEEE",
        "isbn": "1665459069",
        "thumbnail": "",
        "dewey": "",
        "added": "2023-03-27",
        "support": "electronic"
    },
    {
        "id": "99116898857005516",
        "title": "2022 4th International Conference on Control and Robotics (ICCR)",
        "creator": "",
        "date": "2022",
        "publisher": "IEEE",
        "isbn": "1665486414",
        "thumbnail": "",
        "dewey": "",
        "added": "2023-03-27",
        "support": "electronic"
    },
    {
        "id": "99116898857105516",
        "title": "2022 4th International Conference on Circuits, Control, Communication and Computing (I4C)",
        "creator": "",
        "date": "2022",
        "publisher": "IEEE",
        "isbn": "9798350397482",
        "thumbnail": "",
        "dewey": "",
        "added": "2023-03-27",
        "support": "electronic"
    },
    {
        "id": "99116898857205516",
        "title": "2022 4th International Conference on Applied Machine Learning (ICAML)",
        "creator": "",
        "date": "2022",
        "publisher": "IEEE",
        "isbn": "1665462655",
        "thumbnail": "",
        "dewey": "",
        "added": "2023-03-27",
        "support": "electronic"
    },
    {
        "id": "99116898857305516",
        "title": "2022 3rd International Conference on Communication, Computing and Industry 4.0 (C2I4)",
        "creator": "",
        "date": "2022",
        "publisher": "IEEE",
        "isbn": "1665474971",
        "thumbnail": "",
        "dewey": "",
        "added": "2023-03-27",
        "support": "electronic"
    },
    {
        "id": "99116898857405516",
        "title": "Third International Seminar on Artificial Intelligence, Networking, and Information Technology (AINIT 2022)",
        "creator": "",
        "date": "2023",
        "publisher": "SPIE",
        "isbn": "1510662979",
        "thumbnail": "",
        "dewey": "",
        "added": "2023-03-27",
        "support": "electronic"
    },
    {
        "id": "99116898857505516",
        "title": "Third International Conference on Computer Vision and Information Technology (CVIT 2022)",
        "creator": "",
        "date": "2023",
        "publisher": "SPIE",
        "isbn": "1510663045",
        "thumbnail": "",
        "dewey": "",
        "added": "2023-03-27",
        "support": "electronic"
    },
    {
        "id": "99116898857605516",
        "title": "Second International Conference on Green Communication, Network, and Internet of Things (CNIoT 2022)",
        "creator": "",
        "date": "2023",
        "publisher": "SPIE",
        "isbn": "1510662944",
        "thumbnail": "",
        "dewey": "",
        "added": "2023-03-27",
        "support": "electronic"
    },
    {
        "id": "990063000340205516",
        "title": "Hydrodynamic instabilities",
        "creator": "",
        "date": "2011",
        "publisher": "Cambridge University Press",
        "isbn": "0521769264",
        "thumbnail": "http://books.google.com/books/content?id=L9PEtAEACAAJ&printsec=frontcover&img=1&zoom=1&source=gbs_api",
        "dewey": "Engineering and allied operations",
        "added": "2023-03-21",
        "support": "physical"
    },
    {
        "id": "990069915690205516",
        "title": "Apprendre \u00e0 programmer avec Python 3 avec 60 pages d'exercices corrig\u00e9s! ...",
        "creator": "Swinnen, G\u00e9rard 19..-....",
        "date": "2012",
        "publisher": "Eyrolles",
        "isbn": "9782212134346",
        "thumbnail": "http://books.google.com/books/content?id=HxlsQxv8V6kC&printsec=frontcover&img=1&zoom=1&source=gbs_api",
        "dewey": "",
        "added": "2023-03-21",
        "support": "physical"
    },
    {
        "id": "990059840850205516",
        "title": "Instabilit\u00e9s hydrodynamiques",
        "creator": "",
        "date": "2007",
        "publisher": "EDP Sciences",
        "isbn": "9782868839855",
        "thumbnail": "http://books.google.com/books/content?id=QMw_WEL-fzsC&printsec=frontcover&img=1&zoom=1&source=gbs_api",
        "dewey": "",
        "added": "2023-03-14",
        "support": "physical"
    },
    {
        "id": "990108957440205516",
        "title": "Accattone magazine on architecture",
        "creator": "",
        "date": "2014-",
        "publisher": "Accattone",
        "isbn": "",
        "thumbnail": "",
        "dewey": "",
        "added": "2023-03-09",
        "support": "physical"
    },
    {
        "id": "990040136020205516",
        "title": "Le jardin plan\u00e9taire [r\u00e9concilier l'homme et la nature]",
        "creator": "Cl\u00e9ment, Gilles",
        "date": "1999",
        "publisher": "A Michel",
        "isbn": "2226111522",
        "thumbnail": "",
        "dewey": "",
        "added": "2023-03-02",
        "support": "physical"
    },
    {
        "id": "99116866962205516",
        "title": "Hydrology an introduction",
        "creator": "Brutsaert, Wilfried 1934-",
        "date": "2023",
        "publisher": "Cambridge University Press",
        "isbn": "9781107135277",
        "thumbnail": "http://books.google.com/books/content?id=FV6lEAAAQBAJ&printsec=frontcover&img=1&zoom=1&edge=curl&source=gbs_api",
        "dewey": "",
        "added": "2023-02-21",
        "support": "physical"
    },
    {
        "id": "99116841678005516",
        "title": "Writing architectural history evidence and narrative in the Twenty-First Century",
        "creator": "Aggregate",
        "date": "[2021]",
        "publisher": "University of Pittsburgh Press",
        "isbn": "082294684X",
        "thumbnail": "http://books.google.com/books/content?id=gCIMzgEACAAJ&printsec=frontcover&img=1&zoom=1&source=gbs_api",
        "dewey": "Architecture",
        "added": "2023-02-13",
        "support": "physical"
    },
    {
        "id": "99116813974505516",
        "title": "Built",
        "creator": "Olgiati, Valerio 1958-",
        "date": "[2022]",
        "publisher": "Park Books",
        "isbn": "3038602833",
        "thumbnail": "http://books.google.com/books/content?id=G5vUzgEACAAJ&printsec=frontcover&img=1&zoom=1&source=gbs_api",
        "dewey": "Architecture",
        "added": "2023-02-07",
        "support": "physical"
    },
    {
        "id": "990061462740205516",
        "title": "Tarzans in the media forest",
        "creator": "It\u014d, Toyoo 1941-",
        "date": "2011",
        "publisher": "Architectural Association",
        "isbn": "1902902904",
        "thumbnail": "http://books.google.com/books/content?id=UVTLbwAACAAJ&printsec=frontcover&img=1&zoom=1&source=gbs_api",
        "dewey": "Architecture",
        "added": "2023-01-26",
        "support": "physical"
    },
    {
        "id": "99116800163905516",
        "title": "SSA-based compiler design",
        "creator": "",
        "date": "[2023]",
        "publisher": "Springer International Publishing",
        "isbn": "9783030805142",
        "thumbnail": "http://books.google.com/books/content?id=zS54zgEACAAJ&printsec=frontcover&img=1&zoom=1&source=gbs_api",
        "dewey": "",
        "added": "2023-01-25",
        "support": "physical"
    },
    {
        "id": "990074897390205516",
        "title": "MAP Master of architecture projects ...",
        "creator": "",
        "date": "[2009]-",
        "publisher": "Ecole Polytechnique F\u00e9d\u00e9rale de Lausanne",
        "isbn": "9782839910798",
        "thumbnail": "",
        "dewey": "",
        "added": "2023-01-23",
        "support": "physical"
    },
    {
        "id": "990108842780205516",
        "title": "Microeconomics",
        "creator": "Perloff, Jeffrey M. 1950- Verfasser",
        "date": "[2018]",
        "publisher": "Pearson",
        "isbn": "0134519531",
        "thumbnail": "http://books.google.com/books/content?id=iIdavgAACAAJ&printsec=frontcover&img=1&zoom=1&source=gbs_api",
        "dewey": "Production",
        "added": "2023-01-17",
        "support": "physical"
    },
    {
        "id": "99116852161605516",
        "title": "Digitised Newspapers - A New Eldorado for Historians? Reflections on Tools, Methodology and Epistemology",
        "creator": "",
        "date": "[2023]",
        "publisher": "De Gruyter Oldenbourg",
        "isbn": "3110729717",
        "thumbnail": "http://books.google.com/books/content?id=xBSNzgEACAAJ&printsec=frontcover&img=1&zoom=1&source=gbs_api",
        "dewey": "",
        "added": "2023-01-17",
        "support": "physical"
    },
    {
        "id": "99116776311205516",
        "title": "Building with paper architecture and construction",
        "creator": "",
        "date": "[2023]",
        "publisher": "Birkha\u0308user Verlag GmbH",
        "isbn": "3035621535",
        "thumbnail": "http://books.google.com/books/content?id=hDBpzgEACAAJ&printsec=frontcover&img=1&zoom=1&source=gbs_api",
        "dewey": "Architecture",
        "added": "2023-01-16",
        "support": "physical"
    },
    {
        "id": "99116852161405516",
        "title": "Beyond buildings 3XN GXN",
        "creator": "",
        "date": "[2020]",
        "publisher": "The Danish Architectural Press",
        "isbn": "9788774074380",
        "thumbnail": "http://books.google.com/books/content?id=-hQkzgEACAAJ&printsec=frontcover&img=1&zoom=1&source=gbs_api",
        "dewey": "",
        "added": "2023-01-16",
        "support": "physical"
    },
    {
        "id": "99116868762305516",
        "title": "Architecture des Ordinateurs",
        "creator": "Benmohammed, Mohamed",
        "date": "[2017]",
        "publisher": "Noor Publishing",
        "isbn": "9783330967359",
        "thumbnail": "",
        "dewey": "Computer programming, programs, data, security",
        "added": "2023-01-09",
        "support": "physical"
    },
    {
        "id": "99116756501705516",
        "title": "Oscar Niemeyer the mondadori building",
        "creator": "Dulio, Roberto 1971-",
        "date": "[2017]",
        "publisher": "Electa",
        "isbn": "9788891815101",
        "thumbnail": "http://books.google.com/books/content?id=fHeREAAAQBAJ&printsec=frontcover&img=1&zoom=1&source=gbs_api",
        "dewey": "",
        "added": "2022-12-19",
        "support": "physical"
    },
    {
        "id": "99116869256405516",
        "title": "R\u00e9parer l'eau",
        "creator": "Rey, Olivier 1964-....",
        "date": "[2021]",
        "publisher": "Stock",
        "isbn": "9782234091054",
        "thumbnail": "",
        "dewey": "Philosophy & psychology",
        "added": "2022-11-23",
        "support": "physical"
    },
    {
        "id": "99116869256505516",
        "title": "Une pluie d'oiseaux",
        "creator": "Mac\u00e9, Marielle 1973-....",
        "date": "[2022]",
        "publisher": "\u00c9ditions Corti",
        "isbn": "9782714312785",
        "thumbnail": "",
        "dewey": "Literatures of Romance languages",
        "added": "2022-11-23",
        "support": "physical"
    },
    {
        "id": "99116869559305516",
        "title": "La bombe",
        "creator": "Alcante 1970- Verfasser",
        "date": "[2020]",
        "publisher": "Gl\u00e9nat",
        "isbn": "9782344020630",
        "thumbnail": "http://books.google.com/books/content?id=Y6VgzQEACAAJ&printsec=frontcover&img=1&zoom=1&source=gbs_api",
        "dewey": "",
        "added": "2022-11-23",
        "support": "physical"
    },
    {
        "id": "99116869559405516",
        "title": "Living and working",
        "creator": "Dogma Bruxelles, Belgique",
        "date": "[2022]",
        "publisher": "MIT Press",
        "isbn": "9780262543514",
        "thumbnail": "http://books.google.com/books/content?id=FLxNEAAAQBAJ&printsec=frontcover&img=1&zoom=1&edge=curl&source=gbs_api",
        "dewey": "Architecture",
        "added": "2022-11-23",
        "support": "physical"
    },
    {
        "id": "99116804774505516",
        "title": "Adolescent-to-parent violence and abuse applying research to policy and practice",
        "creator": "McCloud, Elizabeth",
        "date": "[2021]",
        "publisher": "Palgrave Macmillan",
        "isbn": "9783030825829",
        "thumbnail": "http://books.google.com/books/content?id=gpCJzgEACAAJ&printsec=frontcover&img=1&zoom=1&source=gbs_api",
        "dewey": "Social problems and services to groups",
        "added": "2022-11-21",
        "support": "physical"
    },
    {
        "id": "99116735350305516",
        "title": "Kay Fisker Danish functionalism and block-based housing",
        "creator": "Clancy, Andrew",
        "date": "2022",
        "publisher": "Lund Humphries",
        "isbn": "1848224052",
        "thumbnail": "http://books.google.com/books/content?id=zpMLyAEACAAJ&printsec=frontcover&img=1&zoom=1&source=gbs_api",
        "dewey": "Architecture from 1400",
        "added": "2022-11-16",
        "support": "physical"
    },
    {
        "id": "99116850262205516",
        "title": "Fake AI",
        "creator": "",
        "date": "2021",
        "publisher": "Meatspace Press",
        "isbn": "9781913824020",
        "thumbnail": "http://books.google.com/books/content?id=S2DmzgEACAAJ&printsec=frontcover&img=1&zoom=1&source=gbs_api",
        "dewey": "Social sciences",
        "added": "2022-11-16",
        "support": "physical"
    },
    {
        "id": "99116868762005516",
        "title": "Ailanthus altissima une monographie situ\u00e9e de l'ailante",
        "creator": "Boudvin, Simon artiste 1979-....",
        "date": "2021",
        "publisher": "B42",
        "isbn": "9782490077434",
        "thumbnail": "",
        "dewey": "Architecture",
        "added": "2022-11-16",
        "support": "physical"
    },
    {
        "id": "99116868762105516",
        "title": "A\u00e9roports, repr\u00e9sentations et exp\u00e9rimentations en architecture",
        "creator": "Estevez, Daniel 1962-",
        "date": "[2012]",
        "publisher": "L'Harmattan",
        "isbn": "2296961819",
        "thumbnail": "http://books.google.com/books/content?id=DqU2bQiKOH4C&printsec=frontcover&img=1&zoom=1&edge=curl&source=gbs_api",
        "dewey": "Public structures",
        "added": "2022-11-16",
        "support": "physical"
    },
    {
        "id": "99116868762205516",
        "title": "Conception non formelle en architecture exp\u00e9riences d'apprentissage et pratiques de conception",
        "creator": "Estevez, Daniel 1962- Verfasser",
        "date": "[2015]",
        "publisher": "l'Harmattan",
        "isbn": "9782343072951",
        "thumbnail": "http://books.google.com/books/content?id=wkrSCgAAQBAJ&printsec=frontcover&img=1&zoom=1&edge=curl&source=gbs_api",
        "dewey": "Landscape architecture (Landscape design)",
        "added": "2022-11-16",
        "support": "physical"
    },
    {
        "id": "99116869561405516",
        "title": "Le v\u00e9ritable enjeu de l'histoire est la contemporan\u00e9it\u00e9 m\u00e9langes offerts \u00e0 Joseph Abram",
        "creator": "",
        "date": "[2022]",
        "publisher": "J-M Place",
        "isbn": "9782383580096",
        "thumbnail": "",
        "dewey": "Architecture",
        "added": "2022-11-16",
        "support": "physical"
    },
    {
        "id": "99116869260005516",
        "title": "Forensic science a sociological introduction",
        "creator": "Lawless, Christopher",
        "date": "2022",
        "publisher": "Routledge",
        "isbn": "0367648067",
        "thumbnail": "http://books.google.com/books/content?id=SDqezgEACAAJ&printsec=frontcover&img=1&zoom=1&source=gbs_api",
        "dewey": "",
        "added": "2022-11-14",
        "support": "physical"
    },
    {
        "id": "99116851962005516",
        "title": "Physics experiments with Arduino and smartphones",
        "creator": "Organtini, Giovanni",
        "date": "[2021]",
        "publisher": "Springer",
        "isbn": "3030651398",
        "thumbnail": "http://books.google.com/books/content?id=dST6zQEACAAJ&printsec=frontcover&img=1&zoom=1&source=gbs_api",
        "dewey": "",
        "added": "2022-11-08",
        "support": "physical"
    },
    {
        "id": "99116853161805516",
        "title": "De l'assemblage au montage cin\u00e9matographique instauration et standardisation d'une pratique",
        "creator": "Gaudreault, Andr\u00e9 1952-",
        "date": "[2022]",
        "publisher": "Les Presses de l'Universit\u00e9 de Montr\u00e9al",
        "isbn": "2760646483",
        "thumbnail": "",
        "dewey": "Cinematography and videography",
        "added": "2022-11-08",
        "support": "physical"
    },
    {
        "id": "99116867861605516",
        "title": "Chimie organique expe\u0301rimentale /",
        "creator": "Perrio, St\u00e9phane 1966-.... Auteur.",
        "date": "DL 2022.",
        "publisher": "Dunod",
        "isbn": "9782100836239",
        "thumbnail": "",
        "dewey": "",
        "added": "2022-11-08",
        "support": "physical"
    },
    {
        "id": "99116867861805516",
        "title": "Magique atome comment le tableau des \u00e9l\u00e9ments peut tout expliquer",
        "creator": "James, Tim professeur de sciences 19..-....",
        "date": "[2022]",
        "publisher": "Dunod",
        "isbn": "9782100839216",
        "thumbnail": "",
        "dewey": "Chemistry and allied sciences",
        "added": "2022-11-08",
        "support": "physical"
    },
    {
        "id": "99116868462005516",
        "title": "Excel 2021 pour les nuls",
        "creator": "Harvey, Greg 1949-....",
        "date": "[2021]",
        "publisher": "First Interactive",
        "isbn": "9782412073490",
        "thumbnail": "",
        "dewey": "Computer programming, programs, data, security",
        "added": "2022-11-08",
        "support": "physical"
    },
    {
        "id": "99116868462105516",
        "title": "Programmer avec Arduino en s'amusant pour les nuls",
        "creator": "Engler, Oliver",
        "date": "DL 2021",
        "publisher": "First interactive",
        "isbn": "2412070032",
        "thumbnail": "",
        "dewey": "Applied physics",
        "added": "2022-11-08",
        "support": "physical"
    },
    {
        "id": "99116868462205516",
        "title": "Programmer avec MySQL SQL, transactions, PHP, Java, optimisations, XML, JSON : avec 40 exercices corrig\u00e9s",
        "creator": "Soutou, Christian",
        "date": "[2021]",
        "publisher": "Editions Eyrolles",
        "isbn": "9782416003684",
        "thumbnail": "",
        "dewey": "Computer programming, programs, data, security",
        "added": "2022-11-08",
        "support": "physical"
    },
    {
        "id": "99116868761805516",
        "title": "Enseigner et former psychologie appliqu\u00e9e et p\u00e9dagogies actives : secondaire, sup\u00e9rieur, formation professionnelle",
        "creator": "Parmentier, Jean-Francois 1982-....",
        "date": "[2022]",
        "publisher": "Dunod",
        "isbn": "2100836536",
        "thumbnail": "",
        "dewey": "Education",
        "added": "2022-11-08",
        "support": "physical"
    },
    {
        "id": "99116869260605516",
        "title": "La Science fiction une introduction historique et philosophique",
        "creator": "Hottois, Gilbert",
        "date": "[2022]",
        "publisher": "Librairie philosophique J Vrin",
        "isbn": "9782711630141",
        "thumbnail": "http://books.google.com/books/content?id=goVUzwEACAAJ&printsec=frontcover&img=1&zoom=1&source=gbs_api",
        "dewey": "",
        "added": "2022-11-08",
        "support": "physical"
    },
    {
        "id": "99116858957505516",
        "title": "L'\u0153uvre artisanale dans l'espace urbain atlas bruxellois de la communalit\u00e9",
        "creator": "Decl\u00e8ve, Marine",
        "date": "[2022]",
        "publisher": "M\u0113tisPresses",
        "isbn": "9782940711116",
        "thumbnail": "",
        "dewey": "Area planning and landscape architecture",
        "added": "2022-11-03",
        "support": "physical"
    },
    {
        "id": "99116866961705516",
        "title": "Guide d'architecture Paris Pavillon de l'Arsenal, 1900-2008",
        "creator": "Lapierre, \u00c9ric 1966-",
        "date": "2008",
        "publisher": "Pavillon de l'Arsenal",
        "isbn": "9782354870034",
        "thumbnail": "",
        "dewey": "",
        "added": "2022-11-02",
        "support": "physical"
    },
    {
        "id": "99116867761605516",
        "title": "Architecture and feminism",
        "creator": "",
        "date": "[1996]",
        "publisher": "Princeton Architectural Press",
        "isbn": "1568980434",
        "thumbnail": "http://books.google.com/books/content?id=4V_qAAAAMAAJ&printsec=frontcover&img=1&zoom=1&source=gbs_api",
        "dewey": "Architecture",
        "added": "2022-11-02",
        "support": "physical"
    },
    {
        "id": "99116868062205516",
        "title": "Essays on kitchens",
        "creator": "Czerniewska, Klara 1987- Verfasser",
        "date": "2019",
        "publisher": "Spector Books OHG",
        "isbn": "3959053282",
        "thumbnail": "http://books.google.com/books/content?id=Xe23xQEACAAJ&printsec=frontcover&img=1&zoom=1&source=gbs_api",
        "dewey": "Furniture and accessories",
        "added": "2022-11-02",
        "support": "physical"
    },
    {
        "id": "99116869260105516",
        "title": "Forensic chemistry of substance misuse a guide to drug control",
        "creator": "King, Leslie A.",
        "date": "[2022]",
        "publisher": "Royal Society of Chemistry",
        "isbn": "1839164506",
        "thumbnail": "http://books.google.com/books/content?id=Lk1-EAAAQBAJ&printsec=frontcover&img=1&zoom=1&edge=curl&source=gbs_api",
        "dewey": "Social problems and services to groups",
        "added": "2022-11-02",
        "support": "physical"
    },
    {
        "id": "99116869561505516",
        "title": "Modern heritage reuse, renovation, restoration",
        "creator": "",
        "date": "[2022]",
        "publisher": "Docomomo International; Birkha\u0308user",
        "isbn": "9783035625080",
        "thumbnail": "http://books.google.com/books/content?id=G0anzgEACAAJ&printsec=frontcover&img=1&zoom=1&source=gbs_api",
        "dewey": "Architecture",
        "added": "2022-11-02",
        "support": "physical"
    },
    {
        "id": "99116869561905516",
        "title": "Don't force it, solve it! how to design meaningful and efficient design processes",
        "creator": "Kalmpourtzis, George",
        "date": "[2022]",
        "publisher": "CRC Press",
        "isbn": "9780367505653",
        "thumbnail": "http://books.google.com/books/content?id=ff5DzgEACAAJ&printsec=frontcover&img=1&zoom=1&source=gbs_api",
        "dewey": "Management and auxiliary services",
        "added": "2022-11-02",
        "support": "physical"
    }
]