[
    {
        "id": "99116994862005516",
        "title": "Trusting recovery and desistance the social components model of recovery from addiction and desistance from crime",
        "creator": "Hall, Lauren",
        "date": "[2024]",
        "publisher": "Routledge",
        "isbn": "9780367743475",
        "thumbnail": "",
        "dewey": "Social problems and services to groups",
        "added": "2024-07-04",
        "support": "physical"
    },
    {
        "id": "99116994862105516",
        "title": "Better crime prevention",
        "creator": "Tilley, Nick 1947-",
        "date": "[2024]",
        "publisher": "Routledge",
        "isbn": "9780367404390",
        "thumbnail": "",
        "dewey": "",
        "added": "2024-07-04",
        "support": "physical"
    },
    {
        "id": "99116994862205516",
        "title": "A fortified far right? scrutinizing the threat",
        "creator": "Peth\u0151-Kiss, Katalin ca. 20./21.Jh.",
        "date": "[2024]",
        "publisher": "Routledge",
        "isbn": "9781032708034",
        "thumbnail": "",
        "dewey": "",
        "added": "2024-07-04",
        "support": "physical"
    },
    {
        "id": "99116994862305516",
        "title": "Understanding biosocial criminology a paradigm for the 21st century",
        "creator": "Walsh, Anthony",
        "date": "[2024]",
        "publisher": "Edward Elgar",
        "isbn": "9781035322862",
        "thumbnail": "",
        "dewey": "",
        "added": "2024-07-02",
        "support": "physical"
    },
    {
        "id": "99117003862305516",
        "title": "Cases on forensic and criminological science for criminal detection and avoidance",
        "creator": "",
        "date": "[2024]",
        "publisher": "Information Science Reference",
        "isbn": "1668498006",
        "thumbnail": "",
        "dewey": "Other social problems and services",
        "added": "2024-07-02",
        "support": "physical"
    },
    {
        "id": "99116994862405516",
        "title": "Ethical reasoning in forensic science",
        "creator": "Ferrara, Lyndsie",
        "date": "[2024]",
        "publisher": "Springer",
        "isbn": "9783031583919",
        "thumbnail": "",
        "dewey": "",
        "added": "2024-06-25",
        "support": "physical"
    },
    {
        "id": "99116987762405516",
        "title": "What is sexualized violence? intersectional readings",
        "creator": "Sch\u00e4fer, Jana 1989-",
        "date": "2024",
        "publisher": "Routledge Taylor & Francis Group",
        "isbn": "9781032610573",
        "thumbnail": "",
        "dewey": "Social problems and services to groups",
        "added": "2024-06-13",
        "support": "physical"
    },
    {
        "id": "99116984262005516",
        "title": "Forensic Justice a global perspective",
        "creator": "",
        "date": "2024",
        "publisher": "Routledge",
        "isbn": "9781032629322",
        "thumbnail": "",
        "dewey": "",
        "added": "2024-06-12",
        "support": "physical"
    },
    {
        "id": "99116987062305516",
        "title": "A history of forensic science British beginnings in the twentieth century",
        "creator": "Adam, Alison",
        "date": "[2016]",
        "publisher": "Routledge",
        "isbn": "0415856426",
        "thumbnail": "",
        "dewey": "",
        "added": "2024-06-06",
        "support": "physical"
    },
    {
        "id": "99116982060905516",
        "title": "The crime data handbook",
        "creator": "",
        "date": "2024",
        "publisher": "Bristol University Press",
        "isbn": "9781529232035",
        "thumbnail": "",
        "dewey": "Social sciences",
        "added": "2024-06-05",
        "support": "physical"
    },
    {
        "id": "99116984262105516",
        "title": "White-collar crime an opportunity perspective",
        "creator": "Benson, Michael L. 1950-",
        "date": "2024",
        "publisher": "Routledge",
        "isbn": "1032007192",
        "thumbnail": "",
        "dewey": "Law",
        "added": "2024-06-05",
        "support": "physical"
    },
    {
        "id": "99116987062205516",
        "title": "Combating the exploitation of children in cyberspace emerging research and opportunities",
        "creator": "",
        "date": "[2021]",
        "publisher": "IGI Global Information",
        "isbn": "1799823601",
        "thumbnail": "",
        "dewey": "",
        "added": "2024-06-05",
        "support": "physical"
    },
    {
        "id": "99116982061005516",
        "title": "Marginalised voices in criminology",
        "creator": "",
        "date": "2024",
        "publisher": "Routledge",
        "isbn": "1032198109",
        "thumbnail": "",
        "dewey": "Criminology",
        "added": "2024-05-28",
        "support": "physical"
    },
    {
        "id": "99116984262205516",
        "title": "Character, circumstances, and criminal careers towards a dynamic developmental and life-course criminology",
        "creator": "Wikstro\u0308m, Per-Olof H.",
        "date": "2024",
        "publisher": "Oxford University Press",
        "isbn": "0198865864",
        "thumbnail": "",
        "dewey": "Criminology",
        "added": "2024-05-28",
        "support": "physical"
    },
    {
        "id": "99116980162105516",
        "title": "The Routledge international handbook of homicide investigation",
        "creator": "",
        "date": "2023",
        "publisher": "Routledge",
        "isbn": "1032047267",
        "thumbnail": "",
        "dewey": "",
        "added": "2024-05-23",
        "support": "physical"
    },
    {
        "id": "99116980162205516",
        "title": "Routledge handbook of evidence-based criminal justice practices",
        "creator": "",
        "date": "2024",
        "publisher": "Routledge Taylor & Francis Group",
        "isbn": "1032107340",
        "thumbnail": "",
        "dewey": "Criminology",
        "added": "2024-05-23",
        "support": "physical"
    },
    {
        "id": "99116991559605516",
        "title": "A blueprint for implementing best practice procedures in a digital forensic laboratory meeting the requirements of ISO standards and other best practices",
        "creator": "Watson, David",
        "date": "2024",
        "publisher": "Academic Press",
        "isbn": "0128194790",
        "thumbnail": "",
        "dewey": "",
        "added": "2024-05-23",
        "support": "physical"
    },
    {
        "id": "99116982261405516",
        "title": "Against cybercrime toward a realist criminology of computer crime",
        "creator": "Steinmetz, Kevin F.",
        "date": "2024",
        "publisher": "Routledge Taylor & Francis Group",
        "isbn": "9781032235059",
        "thumbnail": "",
        "dewey": "Law",
        "added": "2024-05-15",
        "support": "physical"
    },
    {
        "id": "99116982261505516",
        "title": "Modern insights and strategies in victimology",
        "creator": "",
        "date": "[2024]",
        "publisher": "Information Science Reference",
        "isbn": "9798369322017",
        "thumbnail": "",
        "dewey": "Social problems and services to groups",
        "added": "2024-05-08",
        "support": "physical"
    },
    {
        "id": "99116980162305516",
        "title": "Crime and the construction of forensic objectivity from 1850",
        "creator": "",
        "date": "[2020]",
        "publisher": "Palgrave Macmillan",
        "isbn": "9783030288365",
        "thumbnail": "",
        "dewey": "Other social problems and services",
        "added": "2024-05-07",
        "support": "physical"
    },
    {
        "id": "99116980162405516",
        "title": "Cyber and digital forensic investigations a law enforcement practitioner\u2019s perspective",
        "creator": "",
        "date": "[2020]",
        "publisher": "Springer",
        "isbn": "9783030471309",
        "thumbnail": "",
        "dewey": "",
        "added": "2024-05-07",
        "support": "physical"
    },
    {
        "id": "99116980961505516",
        "title": "La cybercriminalit\u00e9 approche \u00e9cosyst\u00e9mique de l'espace num\u00e9rique",
        "creator": "Dupont, Beno\u00eet 1972-....",
        "date": "[2024]",
        "publisher": "Armand Colin",
        "isbn": "9782200637965",
        "thumbnail": "",
        "dewey": "Social problems and services; associations",
        "added": "2024-04-30",
        "support": "physical"
    },
    {
        "id": "99116968562305516",
        "title": "The Oxford handbook of evidence-based crime and justice policy",
        "creator": "Welsh, Brandon 1969-",
        "date": "[2024]",
        "publisher": "Oxford University Press",
        "isbn": "0197618111",
        "thumbnail": "",
        "dewey": "Epistemology (Theory of knowledge)",
        "added": "2024-04-09",
        "support": "physical"
    },
    {
        "id": "99116967862405516",
        "title": "Crime, science and policing",
        "creator": "Laycock, Gloria K.",
        "date": "[2024]",
        "publisher": "Routledge",
        "isbn": "0367761777",
        "thumbnail": "",
        "dewey": "Criminology",
        "added": "2024-03-21",
        "support": "physical"
    },
    {
        "id": "99116965162205516",
        "title": "Impact evaluation in practice",
        "creator": "Gertler, Paul 1955-.... Verfasser",
        "date": "[2016]",
        "publisher": "World Bank Group",
        "isbn": "9781464807794",
        "thumbnail": "",
        "dewey": "Production",
        "added": "2024-03-19",
        "support": "physical"
    },
    {
        "id": "99116971762305516",
        "title": "Polices environnementales sous contraintes",
        "creator": "Magnin, L\u00e9o 1993-....",
        "date": "[2024]",
        "publisher": "Rue d'Ulm",
        "isbn": "2728808562",
        "thumbnail": "",
        "dewey": "Other social problems and services",
        "added": "2024-03-13",
        "support": "physical"
    },
    {
        "id": "99116965162305516",
        "title": "Field experiments design, analysis, and interpretation",
        "creator": "Gerber, Alan S. Verfasser",
        "date": "[2012]",
        "publisher": "W W Norton",
        "isbn": "0393979954",
        "thumbnail": "",
        "dewey": "",
        "added": "2024-02-06",
        "support": "physical"
    }
]